pysdkit/__init__.py
pysdkit/_emd/__init__.py
pysdkit/_emd/_find_extrema.py
pysdkit/_emd/_prepare_points.py
pysdkit/_emd/_splines.py
pysdkit/_emd/ceemdan.py
pysdkit/_emd/eemd.py
pysdkit/_emd/efd.py
pysdkit/_emd/emd.py
pysdkit/_emd/memd.py
pysdkit/_emd/remd.py
pysdkit/_emd/tvf_emd.py
pysdkit/_emd/hht/__init__.py
pysdkit/_emd/hht/frequency.py
pysdkit/_emd/hht/hht.py
pysdkit/_emd2d/__init__.py
pysdkit/_emd2d/bemd.py
pysdkit/_emd2d/bmemd.py
pysdkit/_emd2d/emd2d.py
pysdkit/_esmd/__init__.py
pysdkit/_esmd/esmd.py
pysdkit/_ewt/__init__.py
pysdkit/_ewt/ewt.py
pysdkit/_ewt/ewt2d.py
pysdkit/_faemd/__init__.py
pysdkit/_faemd/extrema.py
pysdkit/_faemd/faemd.py
pysdkit/_faemd/faemd2d.py
pysdkit/_faemd/faemd3d.py
pysdkit/_faemd/filter.py
pysdkit/_fmd/__init__.py
pysdkit/_fmd/fmd.py
pysdkit/_fmd/nfmd.py
pysdkit/_hvd/__init__.py
pysdkit/_hvd/hvd.py
pysdkit/_ifd/__init__.py
pysdkit/_itd/__init__.py
pysdkit/_itd/itd.py
pysdkit/_jmd/__init__.py
pysdkit/_jmd/jmd.py
pysdkit/_jmd/mjmd.py
pysdkit/_lmd/__init__.py
pysdkit/_lmd/lmd.py
pysdkit/_lmd/rlmd.py
pysdkit/_osd/__init__.py
pysdkit/_ssa/__init__.py
pysdkit/_ssa/ssa.py
pysdkit/_vmd/__init__.py
pysdkit/_vmd/acmd.py
pysdkit/_vmd/avmd.py
pysdkit/_vmd/ba_acmd.py
pysdkit/_vmd/base.py
pysdkit/_vmd/mvmd.py
pysdkit/_vmd/svmd.py
pysdkit/_vmd/vmd_c.py
pysdkit/_vmd/vmd_f.py
pysdkit/_vmd/vme.py
pysdkit/_vmd2d/__init__.py
pysdkit/_vmd2d/cvmd2d.py
pysdkit/_vmd2d/vmd2d.py
pysdkit/_vncmd/__init__.py
pysdkit/_vncmd/avncmd.py
pysdkit/_vncmd/incmd.py
pysdkit/_vncmd/mncmd.py
pysdkit/_vncmd/vncmd.py
pysdkit/data/__init__.py
pysdkit/data/_add_noise.py
pysdkit/data/_cube.py
pysdkit/data/_generator.py
pysdkit/data/_image.py
pysdkit/data/_models.py
pysdkit/data/_test_univariate.py
pysdkit/data/_time_series.py
pysdkit/data/texture.txt
pysdkit/entropy/__init__.py
pysdkit/entropy/_approxiamte_entropy.py
pysdkit/entropy/_permutation_entropy.py
pysdkit/entropy/_sample_entropy.py
pysdkit/models/__init__.py
pysdkit/models/_base.py
pysdkit/models/_kmeans.py
pysdkit-0.4.23.dist-info/licenses/LICENSE
pysdkit-0.4.23.dist-info/METADATA
pysdkit-0.4.23.dist-info/WHEEL
pysdkit-0.4.23.dist-info/top_level.txt
pysdkit-0.4.23.dist-info/RECORD
