Metadata-Version: 2.4
Name: PySDKit
Version: 0.4.23
Summary: A Python library for signal decomposition algorithms with a unified interface.
Home-page: https://github.com/wwhenxuan/PySDKit
Author: whenxuan, changewam, josefinez, Yuan Feng
Author-email: wwhenxuan@gmail.com
Keywords: signal decomposition,signal processing,machine learning
Classifier: Development Status :: 3 - Alpha
Classifier: Intended Audience :: Science/Research
Classifier: Topic :: Scientific/Engineering :: Mathematics
Classifier: Topic :: Scientific/Engineering :: Artificial Intelligence
Classifier: License :: OSI Approved :: MIT License
Classifier: Programming Language :: Python :: 3.8
Classifier: Programming Language :: Python :: 3.9
Classifier: Programming Language :: Python :: 3.10
Classifier: Programming Language :: Python :: 3.11
Requires-Python: >=3.8
License-File: LICENSE
Requires-Dist: numpy>=1.24.3
Requires-Dist: scipy>=1.11.1
Requires-Dist: matplotlib>=3.7.2
Requires-Dist: tqdm>=4.66.5
Requires-Dist: requests>=2.32.3
Dynamic: author
Dynamic: author-email
Dynamic: classifier
Dynamic: description
Dynamic: description-content-type
Dynamic: home-page
Dynamic: keywords
Dynamic: license-file
Dynamic: requires-dist
Dynamic: requires-python
Dynamic: summary
